LICENSE
README.md
pypi.readme
setup.py
PyJONDB.egg-info/PKG-INFO
PyJONDB.egg-info/SOURCES.txt
PyJONDB.egg-info/dependency_links.txt
PyJONDB.egg-info/requires.txt
PyJONDB.egg-info/top_level.txt
pyjondb/__init__.py
pyjondb/database.py
pyjondb/session.py