Metadata-Version: 2.1
Name: PyJONDB
Version: 2.0
Summary: A lightweight, encrypted JSON-based database with support for collections, document operations, and aggregation.
Home-page: https://tago.works/
Author: t-a-g-o
Author-email: santiago@tago.works
Project-URL: Bug Reports, https://github.com/t-a-g-o/PyJONDB/issues
Project-URL: Source, https://github.com/t-a-g-o/PyJONDB/
Keywords: encryption database,encrypted database,json database,secure storage,lightweight database,document store,fernet encryption,cryptography,data security,data encryption,collections,document operations,aggregation,query,NoSQL,python database,uuid,file-based database,local database,secure json,nested data,tree structure,data management,data linkage,collection linking
Classifier: Development Status :: 4 - Beta
Classifier: Intended Audience :: Developers
Classifier: Topic :: Software Development :: Libraries
Classifier: Programming Language :: Python :: 3.10
Requires-Python: >=3.8
License-File: LICENSE
Requires-Dist: cryptography
